{
  "project_info": {
    "project_number": "369415286358",
    "firebase_url": "https://pomuzemesi-mobile.firebaseio.com",
    "project_id": "pomuzemesi-mobile",
    "storage_bucket": "pomuzemesi-mobile.appspot.com"
  },
  "client": [
    {
      "client_info": {
        "mobilesdk_app_id": "1:369415286358:android:0bb4081717bbecd9ed95f7",
        "android_client_info": {
          "package_name": "cz.applifting.pomuzemesi"
        }
      },
      "oauth_client": [
        {
          "client_id": "369415286358-qtumrunhertuhfhgtcf8jkntuq1cbt1e.apps.googleusercontent.com",
          "client_type": 3
        }
      ],
      "api_key": [
        {
          "current_key": "AIzaSyBNQjJN5w7aBcRZjL7Sthwt1q7PUJaiEno"
        }
      ],
      "services": {
        "appinvite_service": {
          "other_platform_oauth_client": [
            {
              "client_id": "369415286358-qtumrunhertuhfhgtcf8jkntuq1cbt1e.apps.googleusercontent.com",
              "client_type": 3
            }
          ]
        }
      }
    }
  ],
  "configuration_version": "1"
}